fedoidcrp
fedoidcrp/oidc
