Metadata-Version: 1.1
Name: fedoidcrp
Version: 0.2.1
Summary: Python implementation of a federation aware OpenID Connect RP
Home-page: https://github.com/IdentityPython/fedoidcmsg/
Author: Roland Hedberg
Author-email: roland@catalogix.se
License: Apache 2.0
Platform: UNKNOWN
Classifier: Development Status :: 4 - Beta
Classifier: License :: OSI Approved :: Apache Software License
Classifier: Programming Language :: Python :: 3.4
Classifier: Programming Language :: Python :: 3.5
Classifier: Programming Language :: Python :: 3.6
Classifier: Topic :: Software Development :: Libraries :: Python Modules
